bitscalcpro/__init__.py
bitscalcpro/base_converter.py
bitscalcpro/float_converter.py
bitscalcpro/main.py
bitscalcpro/print_info.py
bitscalcpro/validator.py
bitscalcpro/welcome.py
bitscalcpro-3.0.dist-info/LICENSE
bitscalcpro-3.0.dist-info/METADATA
bitscalcpro-3.0.dist-info/WHEEL
bitscalcpro-3.0.dist-info/entry_points.txt
bitscalcpro-3.0.dist-info/top_level.txt
bitscalcpro-3.0.dist-info/RECORD
