Metadata-Version: 2.1
Name: bitscalcpro
Version: 3.0
Summary: Comprehensive Numeric Converter & Analyzer
Author-email: MuhammadRizwan <mrizwan87@proton.me>
Project-URL: Homepage, https://github.com/muhammadrizwan87/bitscalcpro
Project-URL: Issues, https://github.com/muhammadrizwan87/bitscalcpro/issues
Classifier: Programming Language :: Python :: 3
Classifier: License :: OSI Approved :: MIT License
Classifier: Operating System :: OS Independent
Requires-Python: >=3.8
License-File: LICENSE
